python_sample_app/__init__.py
python_sample_app/main.py
python_sample_app_mackes-1.0.16.dist-info/licenses/LICENSE.md
python_sample_app_mackes-1.0.16.dist-info/METADATA
python_sample_app_mackes-1.0.16.dist-info/WHEEL
python_sample_app_mackes-1.0.16.dist-info/entry_points.txt
python_sample_app_mackes-1.0.16.dist-info/top_level.txt
python_sample_app_mackes-1.0.16.dist-info/RECORD
