Metadata-Version: 2.4
Name: python-sample-app-mackes
Version: 1.0.16
Summary: A sample Python application with CLI entry point
Home-page: https://github.com/mackes/python-sample-app
Author: Your Name
Author-email: you@example.com
License: MIT
Requires-Python: >=3.6
License-File: LICENSE.md
Dynamic: author
Dynamic: author-email
Dynamic: description
Dynamic: description-content-type
Dynamic: home-page
Dynamic: license
Dynamic: license-file
Dynamic: requires-python
Dynamic: summary
